{"Abrasi":[{"id":29,"wilayah":"Aceh","jumlah_kejadian_bencana":12,"meninggal":0,"hilang":0,"terluka":0,"menderita":235,"mengungsi":223,"rumah":74,"pendidikan":0,"kesehatan":0,"peribadatan":0,"fasum":0,"perkantoran":0,"jembatan":0,"pabrik":0,"kios":0,"jenis_bencana":"Abrasi","tahun":2020},{"id":22,"wilayah":"Sumatera Utara","jumlah_kejadian_bencana":1,"meninggal":0,"hilang":0,"terluka":0,"menderita":10,"mengungsi":0,"rumah":2,"pendidikan":0,"kesehatan":0,"peribadatan":0,"fasum":0,"perkantoran":0,"jembatan":0,"pabrik":0,"kios":0,"jenis_bencana":"Abrasi","tahun":2020},{"id":24,"wilayah":"Sumatera Barat","jumlah_kejadian_bencana":4,"meninggal":0,"hilang":0,"terluka":0,"menderita":0,"mengungsi":0,"rumah":56,"pendidikan":0,"kesehatan":0,"peribadatan":0,"fasum":0,"perkantoran":0,"jembatan":0,"pabrik":0,"kios":1,"jenis_bencana":"Abrasi","tahun":2020},{"id":28,"wilayah":"Bengkulu","jumlah_kejadian_bencana":1,"meninggal":0,"hilang":0,"terluka":0,"menderita":0,"mengungsi":0,"rumah":0,"pendidikan":0,"kesehatan":0,"peribadatan":0,"fasum":0,"perkantoran":0,"jembatan":1,"pabrik":0,"kios":0,"jenis_bencana":"Abrasi","tahun":2020},{"id":27,"wilayah":"Lampung","jumlah_kejadian_bencana":2,"meninggal":0,"hilang":0,"terluka":0,"menderita":20,"mengungsi":0,"rumah":3,"pendidikan":0,"kesehatan":0,"peribadatan":1,"fasum":0,"perkantoran":0,"jembatan":0,"pabrik":0,"kios":0,"jenis_bencana":"Abrasi","tahun":2020},{"id":12,"wilayah":"Jawa Barat","jumlah_kejadian_bencana":1,"meninggal":0,"hilang":0,"terluka":0,"menderita":370,"mengungsi":0,"rumah":0,"pendidikan":0,"kesehatan":0,"peribadatan":0,"fasum":0,"perkantoran":0,"jembatan":0,"pabrik":0,"kios":0,"jenis_bencana":"Abrasi","tahun":2020},{"id":5,"wilayah":"Jawa Tengah","jumlah_kejadian_bencana":7,"meninggal":0,"hilang":0,"terluka":0,"menderita":690,"mengungsi":0,"rumah":1,"pendidikan":0,"kesehatan":0,"peribadatan":0,"fasum":0,"perkantoran":0,"jembatan":1,"pabrik":0,"kios":59,"jenis_bencana":"Abrasi","tahun":2020},{"id":4,"wilayah":"DI Yogyakarta","jumlah_kejadian_bencana":1,"meninggal":0,"hilang":0,"terluka":0,"menderita":0,"mengungsi":0,"rumah":0,"pendidikan":0,"kesehatan":0,"peribadatan":0,"fasum":0,"perkantoran":0,"jembatan":0,"pabrik":0,"kios":14,"jenis_bencana":"Abrasi","tahun":2020},{"id":15,"wilayah":"Bali","jumlah_kejadian_bencana":1,"meninggal":0,"hilang":0,"terluka":0,"menderita":0,"mengungsi":0,"rumah":9,"pendidikan":0,"kesehatan":0,"peribadatan":0,"fasum":0,"perkantoran":0,"jembatan":0,"pabrik":0,"kios":0,"jenis_bencana":"Abrasi","tahun":2020},{"id":30,"wilayah":"Kalimantan Barat","jumlah_kejadian_bencana":1,"meninggal":0,"hilang":0,"terluka":0,"menderita":0,"mengungsi":0,"rumah":11,"pendidikan":0,"kesehatan":0,"peribadatan":0,"fasum":0,"perkantoran":0,"jembatan":0,"pabrik":0,"kios":0,"jenis_bencana":"Abrasi","tahun":2020},{"id":31,"wilayah":"Kalimantan Tengah","jumlah_kejadian_bencana":1,"meninggal":0,"hilang":0,"terluka":0,"menderita":0,"mengungsi":0,"rumah":4,"pendidikan":0,"kesehatan":0,"peribadatan":0,"fasum":0,"perkantoran":0,"jembatan":0,"pabrik":0,"kios":0,"jenis_bencana":"Abrasi","tahun":2020},{"id":32,"wilayah":"Kalimantan Selatan","jumlah_kejadian_bencana":1,"meninggal":0,"hilang":0,"terluka":0,"menderita":41,"mengungsi":0,"rumah":10,"pendidikan":0,"kesehatan":0,"peribadatan":0,"fasum":0,"perkantoran":0,"jembatan":0,"pabrik":0,"kios":0,"jenis_bencana":"Abrasi","tahun":2020},{"id":34,"wilayah":"Kalimantan Utara","jumlah_kejadian_bencana":1,"meninggal":0,"hilang":0,"terluka":0,"menderita":0,"mengungsi":25,"rumah":8,"pendidikan":0,"kesehatan":0,"peribadatan":0,"fasum":0,"perkantoran":0,"jembatan":0,"pabrik":0,"kios":0,"jenis_bencana":"Abrasi","tahun":2020},{"id":20,"wilayah":"Sulawesi Utara","jumlah_kejadian_bencana":3,"meninggal":0,"hilang":0,"terluka":0,"menderita":50,"mengungsi":0,"rumah":24,"pendidikan":1,"kesehatan":0,"peribadatan":0,"fasum":0,"perkantoran":0,"jembatan":0,"pabrik":0,"kios":0,"jenis_bencana":"Abrasi","tahun":2020},{"id":10,"wilayah":"Sulawesi Selatan","jumlah_kejadian_bencana":5,"meninggal":0,"hilang":0,"terluka":0,"menderita":1110,"mengungsi":0,"rumah":15,"pendidikan":0,"kesehatan":0,"peribadatan":0,"fasum":0,"perkantoran":0,"jembatan":0,"pabrik":0,"kios":0,"jenis_bencana":"Abrasi","tahun":2020},{"id":3,"wilayah":"Sulawesi Tenggara","jumlah_kejadian_bencana":1,"meninggal":0,"hilang":0,"terluka":0,"menderita":0,"mengungsi":0,"rumah":4,"pendidikan":0,"kesehatan":0,"peribadatan":0,"fasum":0,"perkantoran":0,"jembatan":0,"pabrik":0,"kios":0,"jenis_bencana":"Abrasi","tahun":2020},{"id":8,"wilayah":"Maluku Utara","jumlah_kejadian_bencana":1,"meninggal":0,"hilang":0,"terluka":0,"menderita":0,"mengungsi":180,"rumah":0,"pendidikan":0,"kesehatan":0,"peribadatan":0,"fasum":0,"perkantoran":0,"jembatan":0,"pabrik":0,"kios":0,"jenis_bencana":"Abrasi","tahun":2020}],"Banjir":[{"id":29,"wilayah":"Aceh","jumlah_kejadian_bencana":81,"meninggal":3,"hilang":0,"terluka":0,"menderita":133668,"mengungsi":12279,"rumah":189,"pendidikan":6,"kesehatan":0,"peribadatan":7,"fasum":0,"perkantoran":0,"jembatan":9,"pabrik":0,"kios":21,"jenis_bencana":"Banjir","tahun":2020},{"id":22,"wilayah":"Sumatera Utara","jumlah_kejadian_bencana":76,"meninggal":13,"hilang":4,"terluka":9,"menderita":341450,"mengungsi":22692,"rumah":380,"pendidikan":18,"kesehatan":1,"peribadatan":11,"fasum":0,"perkantoran":1,"jembatan":13,"pabrik":0,"kios":46,"jenis_bencana":"Banjir","tahun":2020},{"id":24,"wilayah":"Sumatera Barat","jumlah_kejadian_bencana":75,"meninggal":3,"hilang":1,"terluka":3,"menderita":22382,"mengungsi":5121,"rumah":125,"pendidikan":14,"kesehatan":1,"peribadatan":11,"fasum":0,"perkantoran":4,"jembatan":32,"pabrik":0,"kios":6,"jenis_bencana":"Banjir","tahun":2020},{"id":16,"wilayah":"Riau","jumlah_kejadian_bencana":19,"meninggal":0,"hilang":0,"terluka":0,"menderita":14972,"mengungsi":140,"rumah":13,"pendidikan":0,"kesehatan":0,"peribadatan":0,"fasum":0,"perkantoran":0,"jembatan":0,"pabrik":0,"kios":0,"jenis_bencana":"Banjir","tahun":2020},{"id":26,"wilayah":"Jambi","jumlah_kejadian_bencana":36,"meninggal":0,"hilang":0,"terluka":0,"menderita":62882,"mengungsi":250,"rumah":2703,"pendidikan":0,"kesehatan":0,"peribadatan":1,"fasum":0,"perkantoran":0,"jembatan":1,"pabrik":0,"kios":0,"jenis_bencana":"Banjir","tahun":2020},{"id":25,"wilayah":"Sumatera Selatan","jumlah_kejadian_bencana":60,"meninggal":1,"hilang":0,"terluka":0,"menderita":36463,"mengungsi":411,"rumah":982,"pendidikan":10,"kesehatan":2,"peribadatan":3,"fasum":0,"perkantoran":0,"jembatan":29,"pabrik":0,"kios":0,"jenis_bencana":"Banjir","tahun":2020},{"id":28,"wilayah":"Bengkulu","jumlah_kejadian_bencana":20,"meninggal":10,"hilang":0,"terluka":0,"menderita":20527,"mengungsi":0,"rumah":422,"pendidikan":11,"kesehatan":1,"peribadatan":4,"fasum":0,"perkantoran":0,"jembatan":14,"pabrik":0,"kios":0,"jenis_bencana":"Banjir","tahun":2020},{"id":27,"wilayah":"Lampung","jumlah_kejadian_bencana":25,"meninggal":0,"hilang":0,"terluka":0,"menderita":13599,"mengungsi":947,"rumah":3948,"pendidikan":1,"kesehatan":0,"peribadatan":3,"fasum":0,"perkantoran":0,"jembatan":2,"pabrik":0,"kios":0,"jenis_bencana":"Banjir","tahun":2020},{"id":23,"wilayah":"Bangka Belitung","jumlah_kejadian_bencana":3,"meninggal":0,"hilang":0,"terluka":0,"menderita":425,"mengungsi":20,"rumah":0,"pendidikan":0,"kesehatan":0,"peribadatan":0,"fasum":0,"perkantoran":0,"jembatan":0,"pabrik":0,"kios":0,"jenis_bencana":"Banjir","tahun":2020},{"id":17,"wilayah":"Kepulauan Riau","jumlah_kejadian_bencana":2,"meninggal":0,"hilang":0,"terluka":0,"menderita":555,"mengungsi":0,"rumah":0,"pendidikan":0,"kesehatan":0,"peribadatan":0,"fasum":0,"perkantoran":0,"jembatan":0,"pabrik":0,"kios":0,"jenis_bencana":"Banjir","tahun":2020},{"id":11,"wilayah":"DKI Jakarta","jumlah_kejadian_bencana":58,"meninggal":20,"hilang":0,"terluka":0,"menderita":67951,"mengungsi":54535,"rumah":0,"pendidikan":0,"kesehatan":0,"peribadatan":0,"fasum":0,"perkantoran":0,"jembatan":0,"pabrik":0,"kios":0,"jenis_bencana":"Banjir","tahun":2020},{"id":12,"wilayah":"Jawa Barat","jumlah_kejadian_bencana":217,"meninggal":30,"hilang":1,"terluka":24,"menderita":1213626,"mengungsi":408030,"rumah":1846,"pendidikan":169,"kesehatan":10,"peribadatan":300,"fasum":0,"perkantoran":0,"jembatan":44,"pabrik":0,"kios":11,"jenis_bencana":"Banjir","tahun":2020},{"id":5,"wilayah":"Jawa Tengah","jumlah_kejadian_bencana":254,"meninggal":11,"hilang":2,"terluka":4,"menderita":264905,"mengungsi":21490,"rumah":526,"pendidikan":7,"kesehatan":1,"peribadatan":4,"fasum":0,"perkantoran":0,"jembatan":19,"pabrik":0,"kios":8,"jenis_bencana":"Banjir","tahun":2020},{"id":4,"wilayah":"DI Yogyakarta","jumlah_kejadian_bencana":6,"meninggal":0,"hilang":0,"terluka":1,"menderita":720,"mengungsi":0,"rumah":1,"pendidikan":0,"kesehatan":0,"peribadatan":2,"fasum":0,"perkantoran":1,"jembatan":0,"pabrik":0,"kios":0,"jenis_bencana":"Banjir","tahun":2020},{"id":7,"wilayah":"Jawa Timur","jumlah_kejadian_bencana":136,"meninggal":6,"hilang":1,"terluka":14,"menderita":296553,"mengungsi":1338,"rumah":381,"pendidikan":11,"kesehatan":0,"peribadatan":37,"fasum":0,"perkantoran":2,"jembatan":22,"pabrik":0,"kios":50,"jenis_bencana":"Banjir","tahun":2020},{"id":6,"wilayah":"Banten","jumlah_kejadian_bencana":47,"meninggal":12,"hilang":0,"terluka":1,"menderita":250738,"mengungsi":24643,"rumah":5065,"pendidikan":4,"kesehatan":2,"peribadatan":2,"fasum":0,"perkantoran":2,"jembatan":2,"pabrik":0,"kios":0,"jenis_bencana":"Banjir","tahun":2020},{"id":15,"wilayah":"Bali","jumlah_kejadian_bencana":4,"meninggal":0,"hilang":0,"terluka":0,"menderita":0,"mengungsi":20,"rumah":3,"pendidikan":1,"kesehatan":0,"peribadatan":0,"fasum":0,"perkantoran":0,"jembatan":0,"pabrik":0,"kios":0,"jenis_bencana":"Banjir","tahun":2020},{"id":1,"wilayah":"Nusa Tenggara Barat","jumlah_kejadian_bencana":40,"meninggal":3,"hilang":0,"terluka":4,"menderita":25940,"mengungsi":0,"rumah":27,"pendidikan":8,"kesehatan":1,"peribadatan":1,"fasum":0,"perkantoran":2,"jembatan":7,"pabrik":0,"kios":0,"jenis_bencana":"Banjir","tahun":2020},{"id":14,"wilayah":"Nusa Tenggara Timur","jumlah_kejadian_bencana":3,"meninggal":0,"hilang":0,"terluka":0,"menderita":2410,"mengungsi":280,"rumah":2,"pendidikan":0,"kesehatan":0,"peribadatan":0,"fasum":0,"perkantoran":0,"jembatan":0,"pabrik":0,"kios":0,"jenis_bencana":"Banjir","tahun":2020},{"id":30,"wilayah":"Kalimantan Barat","jumlah_kejadian_bencana":50,"meninggal":3,"hilang":0,"terluka":0,"menderita":173228,"mengungsi":109634,"rumah":107,"pendidikan":18,"kesehatan":0,"peribadatan":13,"fasum":0,"perkantoran":1,"jembatan":18,"pabrik":0,"kios":0,"jenis_bencana":"Banjir","tahun":2020},{"id":31,"wilayah":"Kalimantan Tengah","jumlah_kejadian_bencana":64,"meninggal":6,"hilang":3,"terluka":0,"menderita":287876,"mengungsi":6230,"rumah":1,"pendidikan":16,"kesehatan":15,"peribadatan":7,"fasum":0,"perkantoran":1,"jembatan":13,"pabrik":0,"kios":0,"jenis_bencana":"Banjir","tahun":2020},{"id":32,"wilayah":"Kalimantan Selatan","jumlah_kejadian_bencana":64,"meninggal":0,"hilang":0,"terluka":0,"menderita":148096,"mengungsi":289,"rumah":0,"pendidikan":1,"kesehatan":1,"peribadatan":2,"fasum":0,"perkantoran":0,"jembatan":5,"pabrik":0,"kios":0,"jenis_bencana":"Banjir","tahun":2020},{"id":33,"wilayah":"Kalimantan Timur","jumlah_kejadian_bencana":22,"meninggal":0,"hilang":0,"terluka":0,"menderita":71048,"mengungsi":46420,"rumah":6,"pendidikan":10,"kesehatan":5,"peribadatan":21,"fasum":0,"perkantoran":0,"jembatan":0,"pabrik":0,"kios":0,"jenis_bencana":"Banjir","tahun":2020},{"id":34,"wilayah":"Kalimantan Utara","jumlah_kejadian_bencana":6,"meninggal":0,"hilang":0,"terluka":0,"menderita":100,"mengungsi":0,"rumah":0,"pendidikan":0,"kesehatan":0,"peribadatan":0,"fasum":0,"perkantoran":0,"jembatan":1,"pabrik":0,"kios":0,"jenis_bencana":"Banjir","tahun":2020},{"id":20,"wilayah":"Sulawesi Utara","jumlah_kejadian_bencana":6,"meninggal":2,"hilang":1,"terluka":0,"menderita":29070,"mengungsi":0,"rumah":7169,"pendidikan":1,"kesehatan":0,"peribadatan":1,"fasum":0,"perkantoran":0,"jembatan":1,"pabrik":0,"kios":12,"jenis_bencana":"Banjir","tahun":2020},{"id":19,"wilayah":"Sulawesi Tengah","jumlah_kejadian_bencana":43,"meninggal":0,"hilang":1,"terluka":1,"menderita":45629,"mengungsi":6416,"rumah":471,"pendidikan":1,"kesehatan":1,"peribadatan":3,"fasum":0,"perkantoran":2,"jembatan":13,"pabrik":0,"kios":0,"jenis_bencana":"Banjir","tahun":2020},{"id":10,"wilayah":"Sulawesi Selatan","jumlah_kejadian_bencana":49,"meninggal":3,"hilang":0,"terluka":0,"menderita":189872,"mengungsi":4771,"rumah":2322,"pendidikan":173,"kesehatan":73,"peribadatan":121,"fasum":0,"perkantoran":51,"jembatan":60,"pabrik":0,"kios":0,"jenis_bencana":"Banjir","tahun":2020},{"id":3,"wilayah":"Sulawesi Tenggara","jumlah_kejadian_bencana":6,"meninggal":0,"hilang":0,"terluka":0,"menderita":20728,"mengungsi":14140,"rumah":50,"pendidikan":11,"kesehatan":4,"peribadatan":62,"fasum":0,"perkantoran":0,"jembatan":3,"pabrik":0,"kios":0,"jenis_bencana":"Banjir","tahun":2020},{"id":2,"wilayah":"Gorontalo","jumlah_kejadian_bencana":23,"meninggal":4,"hilang":1,"terluka":3,"menderita":96919,"mengungsi":25632,"rumah":1865,"pendidikan":18,"kesehatan":4,"peribadatan":2,"fasum":0,"perkantoran":1,"jembatan":13,"pabrik":0,"kios":0,"jenis_bencana":"Banjir","tahun":2020},{"id":18,"wilayah":"Sulawesi Barat","jumlah_kejadian_bencana":3,"meninggal":0,"hilang":0,"terluka":0,"menderita":5268,"mengungsi":2293,"rumah":0,"pendidikan":1,"kesehatan":0,"peribadatan":1,"fasum":0,"perkantoran":0,"jembatan":0,"pabrik":0,"kios":0,"jenis_bencana":"Banjir","tahun":2020},{"id":9,"wilayah":"Maluku","jumlah_kejadian_bencana":8,"meninggal":0,"hilang":0,"terluka":0,"menderita":3549,"mengungsi":55,"rumah":0,"pendidikan":1,"kesehatan":1,"peribadatan":4,"fasum":0,"perkantoran":2,"jembatan":1,"pabrik":0,"kios":6,"jenis_bencana":"Banjir","tahun":2020},{"id":8,"wilayah":"Maluku Utara","jumlah_kejadian_bencana":16,"meninggal":0,"hilang":0,"terluka":0,"menderita":425,"mengungsi":12438,"rumah":173,"pendidikan":0,"kesehatan":0,"peribadatan":0,"fasum":0,"perkantoran":0,"jembatan":10,"pabrik":0,"kios":0,"jenis_bencana":"Banjir","tahun":2020},{"id":21,"wilayah":"Papua Barat","jumlah_kejadian_bencana":3,"meninggal":0,"hilang":0,"terluka":0,"menderita":1650,"mengungsi":0,"rumah":0,"pendidikan":0,"kesehatan":0,"peribadatan":0,"fasum":0,"perkantoran":0,"jembatan":0,"pabrik":0,"kios":0,"jenis_bencana":"Banjir","tahun":2020},{"id":13,"wilayah":"Papua","jumlah_kejadian_bencana":6,"meninggal":2,"hilang":0,"terluka":0,"menderita":490,"mengungsi":540,"rumah":47,"pendidikan":0,"kesehatan":0,"peribadatan":2,"fasum":0,"perkantoran":1,"jembatan":1,"pabrik":0,"kios":2,"jenis_bencana":"Banjir","tahun":2020}],"Gempa Bumi":[{"id":29,"wilayah":"Aceh","jumlah_kejadian_bencana":4,"meninggal":0,"hilang":0,"terluka":0,"menderita":11,"mengungsi":0,"rumah":4,"pendidikan":0,"kesehatan":0,"peribadatan":1,"fasum":0,"perkantoran":0,"jembatan":0,"pabrik":0,"kios":5,"jenis_bencana":"Gempa Bumi","tahun":2020},{"id":22,"wilayah":"Sumatera Utara","jumlah_kejadian_bencana":1,"meninggal":0,"hilang":0,"terluka":0,"menderita":0,"mengungsi":0,"rumah":4,"pendidikan":1,"kesehatan":0,"peribadatan":2,"fasum":0,"perkantoran":0,"jembatan":0,"pabrik":0,"kios":0,"jenis_bencana":"Gempa Bumi","tahun":2020},{"id":12,"wilayah":"Jawa Barat","jumlah_kejadian_bencana":11,"meninggal":0,"hilang":0,"terluka":18,"menderita":3745,"mengungsi":379,"rumah":1464,"pendidikan":8,"kesehatan":0,"peribadatan":11,"fasum":0,"perkantoran":0,"jembatan":0,"pabrik":0,"kios":0,"jenis_bencana":"Gempa Bumi","tahun":2020},{"id":5,"wilayah":"Jawa Tengah","jumlah_kejadian_bencana":1,"meninggal":0,"hilang":0,"terluka":0,"menderita":0,"mengungsi":0,"rumah":1,"pendidikan":0,"kesehatan":0,"peribadatan":0,"fasum":0,"perkantoran":0,"jembatan":0,"pabrik":0,"kios":0,"jenis_bencana":"Gempa Bumi","tahun":2020},{"id":1,"wilayah":"Nusa Tenggara Barat","jumlah_kejadian_bencana":2,"meninggal":0,"hilang":0,"terluka":0,"menderita":0,"mengungsi":0,"rumah":0,"pendidikan":1,"kesehatan":0,"peribadatan":0,"fasum":0,"perkantoran":0,"jembatan":0,"pabrik":0,"kios":0,"jenis_bencana":"Gempa Bumi","tahun":2020},{"id":20,"wilayah":"Sulawesi Utara","jumlah_kejadian_bencana":1,"meninggal":0,"hilang":0,"terluka":2,"menderita":0,"mengungsi":0,"rumah":136,"pendidikan":2,"kesehatan":0,"peribadatan":7,"fasum":0,"perkantoran":2,"jembatan":0,"pabrik":0,"kios":0,"jenis_bencana":"Gempa Bumi","tahun":2020},{"id":19,"wilayah":"Sulawesi Tengah","jumlah_kejadian_bencana":1,"meninggal":0,"hilang":0,"terluka":9,"menderita":0,"mengungsi":0,"rumah":136,"pendidikan":2,"kesehatan":0,"peribadatan":4,"fasum":0,"perkantoran":2,"jembatan":0,"pabrik":0,"kios":0,"jenis_bencana":"Gempa Bumi","tahun":2020},{"id":18,"wilayah":"Sulawesi Barat","jumlah_kejadian_bencana":1,"meninggal":0,"hilang":0,"terluka":1,"menderita":44,"mengungsi":0,"rumah":13,"pendidikan":0,"kesehatan":0,"peribadatan":0,"fasum":0,"perkantoran":0,"jembatan":0,"pabrik":0,"kios":0,"jenis_bencana":"Gempa Bumi","tahun":2020},{"id":9,"wilayah":"Maluku","jumlah_kejadian_bencana":1,"meninggal":0,"hilang":0,"terluka":0,"menderita":25,"mengungsi":0,"rumah":5,"pendidikan":0,"kesehatan":0,"peribadatan":0,"fasum":0,"perkantoran":0,"jembatan":0,"pabrik":0,"kios":0,"jenis_bencana":"Gempa Bumi","tahun":2020},{"id":8,"wilayah":"Maluku Utara","jumlah_kejadian_bencana":4,"meninggal":0,"hilang":0,"terluka":0,"menderita":715,"mengungsi":0,"rumah":312,"pendidikan":0,"kesehatan":0,"peribadatan":0,"fasum":0,"perkantoran":0,"jembatan":0,"pabrik":0,"kios":0,"jenis_bencana":"Gempa Bumi","tahun":2020},{"id":13,"wilayah":"Papua","jumlah_kejadian_bencana":1,"meninggal":0,"hilang":0,"terluka":0,"menderita":0,"mengungsi":5,"rumah":0,"pendidikan":0,"kesehatan":0,"peribadatan":0,"fasum":0,"perkantoran":0,"jembatan":0,"pabrik":0,"kios":0,"jenis_bencana":"Gempa Bumi","tahun":2020}],"Gunung Meletus":[{"id":22,"wilayah":"Sumatera Utara","jumlah_kejadian_bencana":2,"meninggal":0,"hilang":0,"terluka":0,"menderita":0,"mengungsi":0,"rumah":0,"pendidikan":0,"kesehatan":0,"peribadatan":0,"fasum":0,"perkantoran":0,"jembatan":0,"pabrik":0,"kios":0,"jenis_bencana":"Gunung Meletus","tahun":2020},{"id":27,"wilayah":"Lampung","jumlah_kejadian_bencana":1,"meninggal":0,"hilang":0,"terluka":0,"menderita":0,"mengungsi":0,"rumah":0,"pendidikan":0,"kesehatan":0,"peribadatan":0,"fasum":0,"perkantoran":0,"jembatan":0,"pabrik":0,"kios":0,"jenis_bencana":"Gunung Meletus","tahun":2020},{"id":5,"wilayah":"Jawa Tengah","jumlah_kejadian_bencana":8,"meninggal":0,"hilang":0,"terluka":1,"menderita":0,"mengungsi":911,"rumah":0,"pendidikan":0,"kesehatan":0,"peribadatan":0,"fasum":0,"perkantoran":0,"jembatan":0,"pabrik":0,"kios":0,"jenis_bencana":"Gunung Meletus","tahun":2020},{"id":4,"wilayah":"DI Yogyakarta","jumlah_kejadian_bencana":1,"meninggal":0,"hilang":0,"terluka":0,"menderita":0,"mengungsi":225,"rumah":0,"pendidikan":0,"kesehatan":0,"peribadatan":0,"fasum":0,"perkantoran":0,"jembatan":0,"pabrik":0,"kios":0,"jenis_bencana":"Gunung Meletus","tahun":2020},{"id":7,"wilayah":"Jawa Timur","jumlah_kejadian_bencana":1,"meninggal":0,"hilang":1,"terluka":0,"menderita":6490,"mengungsi":335,"rumah":0,"pendidikan":0,"kesehatan":0,"peribadatan":0,"fasum":0,"perkantoran":0,"jembatan":0,"pabrik":0,"kios":0,"jenis_bencana":"Gunung Meletus","tahun":2020},{"id":14,"wilayah":"Nusa Tenggara Timur","jumlah_kejadian_bencana":1,"meninggal":0,"hilang":0,"terluka":0,"menderita":0,"mengungsi":9028,"rumah":0,"pendidikan":0,"kesehatan":0,"peribadatan":0,"fasum":0,"perkantoran":0,"jembatan":0,"pabrik":0,"kios":0,"jenis_bencana":"Gunung Meletus","tahun":2020}],"Kebakaran Hutan":[{"id":29,"wilayah":"Aceh","jumlah_kejadian_bencana":160,"meninggal":0,"hilang":0,"terluka":1,"menderita":0,"mengungsi":0,"rumah":0,"pendidikan":0,"kesehatan":0,"peribadatan":0,"fasum":0,"perkantoran":0,"jembatan":0,"pabrik":0,"kios":0,"jenis_bencana":"Kebakaran Hutan","tahun":2020},{"id":22,"wilayah":"Sumatera Utara","jumlah_kejadian_bencana":17,"meninggal":0,"hilang":0,"terluka":0,"menderita":0,"mengungsi":0,"rumah":0,"pendidikan":0,"kesehatan":0,"peribadatan":0,"fasum":0,"perkantoran":0,"jembatan":0,"pabrik":0,"kios":0,"jenis_bencana":"Kebakaran Hutan","tahun":2020},{"id":24,"wilayah":"Sumatera Barat","jumlah_kejadian_bencana":11,"meninggal":0,"hilang":0,"terluka":0,"menderita":0,"mengungsi":0,"rumah":0,"pendidikan":0,"kesehatan":0,"peribadatan":0,"fasum":0,"perkantoran":0,"jembatan":0,"pabrik":0,"kios":0,"jenis_bencana":"Kebakaran Hutan","tahun":2020},{"id":16,"wilayah":"Riau","jumlah_kejadian_bencana":21,"meninggal":0,"hilang":0,"terluka":0,"menderita":0,"mengungsi":0,"rumah":0,"pendidikan":0,"kesehatan":0,"peribadatan":0,"fasum":0,"perkantoran":0,"jembatan":0,"pabrik":0,"kios":0,"jenis_bencana":"Kebakaran Hutan","tahun":2020},{"id":26,"wilayah":"Jambi","jumlah_kejadian_bencana":57,"meninggal":0,"hilang":0,"terluka":0,"menderita":0,"mengungsi":0,"rumah":0,"pendidikan":0,"kesehatan":0,"peribadatan":0,"fasum":0,"perkantoran":0,"jembatan":0,"pabrik":0,"kios":0,"jenis_bencana":"Kebakaran Hutan","tahun":2020},{"id":25,"wilayah":"Sumatera Selatan","jumlah_kejadian_bencana":7,"meninggal":0,"hilang":0,"terluka":0,"menderita":0,"mengungsi":0,"rumah":0,"pendidikan":0,"kesehatan":0,"peribadatan":0,"fasum":0,"perkantoran":0,"jembatan":0,"pabrik":0,"kios":0,"jenis_bencana":"Kebakaran Hutan","tahun":2020},{"id":23,"wilayah":"Bangka Belitung","jumlah_kejadian_bencana":3,"meninggal":0,"hilang":0,"terluka":0,"menderita":0,"mengungsi":0,"rumah":0,"pendidikan":0,"kesehatan":0,"peribadatan":0,"fasum":0,"perkantoran":0,"jembatan":0,"pabrik":0,"kios":0,"jenis_bencana":"Kebakaran Hutan","tahun":2020},{"id":17,"wilayah":"Kepulauan Riau","jumlah_kejadian_bencana":51,"meninggal":0,"hilang":0,"terluka":0,"menderita":0,"mengungsi":0,"rumah":1,"pendidikan":0,"kesehatan":0,"peribadatan":0,"fasum":0,"perkantoran":0,"jembatan":0,"pabrik":0,"kios":0,"jenis_bencana":"Kebakaran Hutan","tahun":2020},{"id":12,"wilayah":"Jawa Barat","jumlah_kejadian_bencana":13,"meninggal":0,"hilang":0,"terluka":0,"menderita":0,"mengungsi":0,"rumah":0,"pendidikan":0,"kesehatan":0,"peribadatan":0,"fasum":0,"perkantoran":0,"jembatan":0,"pabrik":0,"kios":0,"jenis_bencana":"Kebakaran Hutan","tahun":2020},{"id":5,"wilayah":"Jawa Tengah","jumlah_kejadian_bencana":19,"meninggal":0,"hilang":0,"terluka":0,"menderita":0,"mengungsi":0,"rumah":0,"pendidikan":0,"kesehatan":0,"peribadatan":0,"fasum":0,"perkantoran":0,"jembatan":0,"pabrik":0,"kios":0,"jenis_bencana":"Kebakaran Hutan","tahun":2020},{"id":7,"wilayah":"Jawa Timur","jumlah_kejadian_bencana":13,"meninggal":0,"hilang":0,"terluka":0,"menderita":0,"mengungsi":0,"rumah":0,"pendidikan":0,"kesehatan":0,"peribadatan":0,"fasum":0,"perkantoran":0,"jembatan":0,"pabrik":0,"kios":0,"jenis_bencana":"Kebakaran Hutan","tahun":2020},{"id":6,"wilayah":"Banten","jumlah_kejadian_bencana":2,"meninggal":0,"hilang":0,"terluka":0,"menderita":0,"mengungsi":0,"rumah":0,"pendidikan":0,"kesehatan":0,"peribadatan":0,"fasum":0,"perkantoran":0,"jembatan":0,"pabrik":0,"kios":0,"jenis_bencana":"Kebakaran Hutan","tahun":2020},{"id":1,"wilayah":"Nusa Tenggara Barat","jumlah_kejadian_bencana":3,"meninggal":0,"hilang":0,"terluka":0,"menderita":0,"mengungsi":0,"rumah":0,"pendidikan":0,"kesehatan":0,"peribadatan":0,"fasum":0,"perkantoran":0,"jembatan":0,"pabrik":0,"kios":0,"jenis_bencana":"Kebakaran Hutan","tahun":2020},{"id":14,"wilayah":"Nusa Tenggara Timur","jumlah_kejadian_bencana":4,"meninggal":0,"hilang":0,"terluka":0,"menderita":0,"mengungsi":0,"rumah":0,"pendidikan":0,"kesehatan":0,"peribadatan":0,"fasum":0,"perkantoran":0,"jembatan":0,"pabrik":0,"kios":0,"jenis_bencana":"Kebakaran Hutan","tahun":2020},{"id":30,"wilayah":"Kalimantan Barat","jumlah_kejadian_bencana":6,"meninggal":0,"hilang":0,"terluka":0,"menderita":0,"mengungsi":0,"rumah":0,"pendidikan":0,"kesehatan":0,"peribadatan":0,"fasum":0,"perkantoran":0,"jembatan":0,"pabrik":0,"kios":0,"jenis_bencana":"Kebakaran Hutan","tahun":2020},{"id":31,"wilayah":"Kalimantan Tengah","jumlah_kejadian_bencana":22,"meninggal":0,"hilang":0,"terluka":0,"menderita":0,"mengungsi":0,"rumah":0,"pendidikan":0,"kesehatan":0,"peribadatan":0,"fasum":0,"perkantoran":0,"jembatan":0,"pabrik":0,"kios":0,"jenis_bencana":"Kebakaran Hutan","tahun":2020},{"id":32,"wilayah":"Kalimantan Selatan","jumlah_kejadian_bencana":86,"meninggal":0,"hilang":0,"terluka":0,"menderita":0,"mengungsi":0,"rumah":0,"pendidikan":0,"kesehatan":0,"peribadatan":0,"fasum":0,"perkantoran":0,"jembatan":0,"pabrik":0,"kios":0,"jenis_bencana":"Kebakaran Hutan","tahun":2020},{"id":33,"wilayah":"Kalimantan Timur","jumlah_kejadian_bencana":70,"meninggal":0,"hilang":0,"terluka":0,"menderita":0,"mengungsi":0,"rumah":0,"pendidikan":0,"kesehatan":0,"peribadatan":0,"fasum":0,"perkantoran":0,"jembatan":0,"pabrik":0,"kios":0,"jenis_bencana":"Kebakaran Hutan","tahun":2020},{"id":34,"wilayah":"Kalimantan Utara","jumlah_kejadian_bencana":47,"meninggal":0,"hilang":0,"terluka":3,"menderita":0,"mengungsi":0,"rumah":0,"pendidikan":0,"kesehatan":0,"peribadatan":0,"fasum":0,"perkantoran":0,"jembatan":0,"pabrik":0,"kios":0,"jenis_bencana":"Kebakaran Hutan","tahun":2020},{"id":19,"wilayah":"Sulawesi Tengah","jumlah_kejadian_bencana":1,"meninggal":0,"hilang":0,"terluka":0,"menderita":0,"mengungsi":0,"rumah":0,"pendidikan":0,"kesehatan":0,"peribadatan":0,"fasum":0,"perkantoran":0,"jembatan":0,"pabrik":0,"kios":0,"jenis_bencana":"Kebakaran Hutan","tahun":2020},{"id":9,"wilayah":"Maluku","jumlah_kejadian_bencana":6,"meninggal":0,"hilang":0,"terluka":0,"menderita":7,"mengungsi":0,"rumah":0,"pendidikan":0,"kesehatan":0,"peribadatan":0,"fasum":0,"perkantoran":0,"jembatan":0,"pabrik":0,"kios":0,"jenis_bencana":"Kebakaran Hutan","tahun":2020}],"Kekeringan":[{"id":29,"wilayah":"Aceh","jumlah_kejadian_bencana":1,"meninggal":0,"hilang":0,"terluka":0,"menderita":0,"mengungsi":0,"rumah":0,"pendidikan":0,"kesehatan":0,"peribadatan":0,"fasum":0,"perkantoran":0,"jembatan":0,"pabrik":0,"kios":0,"jenis_bencana":"Kekeringan","tahun":2020},{"id":25,"wilayah":"Sumatera Selatan","jumlah_kejadian_bencana":1,"meninggal":0,"hilang":0,"terluka":0,"menderita":1000,"mengungsi":0,"rumah":0,"pendidikan":0,"kesehatan":0,"peribadatan":0,"fasum":0,"perkantoran":0,"jembatan":0,"pabrik":0,"kios":0,"jenis_bencana":"Kekeringan","tahun":2020},{"id":12,"wilayah":"Jawa Barat","jumlah_kejadian_bencana":5,"meninggal":0,"hilang":0,"terluka":0,"menderita":78983,"mengungsi":0,"rumah":0,"pendidikan":0,"kesehatan":0,"peribadatan":0,"fasum":0,"perkantoran":0,"jembatan":0,"pabrik":0,"kios":0,"jenis_bencana":"Kekeringan","tahun":2020},{"id":5,"wilayah":"Jawa Tengah","jumlah_kejadian_bencana":7,"meninggal":0,"hilang":0,"terluka":0,"menderita":42573,"mengungsi":0,"rumah":0,"pendidikan":0,"kesehatan":0,"peribadatan":0,"fasum":0,"perkantoran":0,"jembatan":0,"pabrik":0,"kios":0,"jenis_bencana":"Kekeringan","tahun":2020},{"id":7,"wilayah":"Jawa Timur","jumlah_kejadian_bencana":2,"meninggal":0,"hilang":0,"terluka":0,"menderita":0,"mengungsi":0,"rumah":0,"pendidikan":0,"kesehatan":0,"peribadatan":0,"fasum":0,"perkantoran":0,"jembatan":0,"pabrik":0,"kios":0,"jenis_bencana":"Kekeringan","tahun":2020},{"id":1,"wilayah":"Nusa Tenggara Barat","jumlah_kejadian_bencana":9,"meninggal":0,"hilang":0,"terluka":0,"menderita":742657,"mengungsi":0,"rumah":0,"pendidikan":0,"kesehatan":0,"peribadatan":0,"fasum":0,"perkantoran":0,"jembatan":0,"pabrik":0,"kios":0,"jenis_bencana":"Kekeringan","tahun":2020},{"id":14,"wilayah":"Nusa Tenggara Timur","jumlah_kejadian_bencana":1,"meninggal":0,"hilang":0,"terluka":0,"menderita":742657,"mengungsi":0,"rumah":0,"pendidikan":0,"kesehatan":0,"peribadatan":0,"fasum":0,"perkantoran":0,"jembatan":0,"pabrik":0,"kios":0,"jenis_bencana":"Kekeringan","tahun":2020}],"Puting Beliung":[{"id":29,"wilayah":"Aceh","jumlah_kejadian_bencana":98,"meninggal":2,"hilang":6,"terluka":8,"menderita":1763,"mengungsi":170,"rumah":553,"pendidikan":7,"kesehatan":0,"peribadatan":2,"fasum":0,"perkantoran":1,"jembatan":1,"pabrik":0,"kios":20,"jenis_bencana":"Puting Beliung","tahun":2020},{"id":22,"wilayah":"Sumatera Utara","jumlah_kejadian_bencana":40,"meninggal":1,"hilang":0,"terluka":20,"menderita":1614,"mengungsi":235,"rumah":2649,"pendidikan":1,"kesehatan":0,"peribadatan":4,"fasum":0,"perkantoran":0,"jembatan":1,"pabrik":0,"kios":0,"jenis_bencana":"Puting Beliung","tahun":2020},{"id":24,"wilayah":"Sumatera Barat","jumlah_kejadian_bencana":93,"meninggal":0,"hilang":0,"terluka":2,"menderita":194,"mengungsi":0,"rumah":221,"pendidikan":10,"kesehatan":1,"peribadatan":2,"fasum":0,"perkantoran":1,"jembatan":0,"pabrik":0,"kios":15,"jenis_bencana":"Puting Beliung","tahun":2020},{"id":16,"wilayah":"Riau","jumlah_kejadian_bencana":10,"meninggal":0,"hilang":0,"terluka":1,"menderita":5,"mengungsi":82,"rumah":81,"pendidikan":1,"kesehatan":0,"peribadatan":1,"fasum":0,"perkantoran":0,"jembatan":0,"pabrik":0,"kios":0,"jenis_bencana":"Puting Beliung","tahun":2020},{"id":26,"wilayah":"Jambi","jumlah_kejadian_bencana":7,"meninggal":1,"hilang":0,"terluka":0,"menderita":470,"mengungsi":0,"rumah":186,"pendidikan":1,"kesehatan":0,"peribadatan":0,"fasum":0,"perkantoran":0,"jembatan":0,"pabrik":0,"kios":0,"jenis_bencana":"Puting Beliung","tahun":2020},{"id":25,"wilayah":"Sumatera Selatan","jumlah_kejadian_bencana":15,"meninggal":0,"hilang":0,"terluka":0,"menderita":24,"mengungsi":0,"rumah":233,"pendidikan":8,"kesehatan":0,"peribadatan":0,"fasum":0,"perkantoran":0,"jembatan":0,"pabrik":0,"kios":0,"jenis_bencana":"Puting Beliung","tahun":2020},{"id":28,"wilayah":"Bengkulu","jumlah_kejadian_bencana":8,"meninggal":2,"hilang":0,"terluka":0,"menderita":280,"mengungsi":0,"rumah":70,"pendidikan":1,"kesehatan":0,"peribadatan":0,"fasum":0,"perkantoran":3,"jembatan":0,"pabrik":0,"kios":0,"jenis_bencana":"Puting Beliung","tahun":2020},{"id":27,"wilayah":"Lampung","jumlah_kejadian_bencana":15,"meninggal":2,"hilang":0,"terluka":10,"menderita":615,"mengungsi":70,"rumah":606,"pendidikan":1,"kesehatan":0,"peribadatan":0,"fasum":0,"perkantoran":0,"jembatan":0,"pabrik":0,"kios":0,"jenis_bencana":"Puting Beliung","tahun":2020},{"id":23,"wilayah":"Bangka Belitung","jumlah_kejadian_bencana":15,"meninggal":0,"hilang":0,"terluka":0,"menderita":539,"mengungsi":4,"rumah":124,"pendidikan":0,"kesehatan":0,"peribadatan":0,"fasum":0,"perkantoran":0,"jembatan":0,"pabrik":0,"kios":0,"jenis_bencana":"Puting Beliung","tahun":2020},{"id":17,"wilayah":"Kepulauan Riau","jumlah_kejadian_bencana":10,"meninggal":0,"hilang":0,"terluka":3,"menderita":258,"mengungsi":12,"rumah":69,"pendidikan":0,"kesehatan":0,"peribadatan":0,"fasum":0,"perkantoran":0,"jembatan":0,"pabrik":0,"kios":0,"jenis_bencana":"Puting Beliung","tahun":2020},{"id":11,"wilayah":"DKI Jakarta","jumlah_kejadian_bencana":1,"meninggal":0,"hilang":0,"terluka":3,"menderita":517,"mengungsi":0,"rumah":134,"pendidikan":0,"kesehatan":0,"peribadatan":0,"fasum":0,"perkantoran":0,"jembatan":0,"pabrik":0,"kios":0,"jenis_bencana":"Puting Beliung","tahun":2020},{"id":12,"wilayah":"Jawa Barat","jumlah_kejadian_bencana":452,"meninggal":4,"hilang":0,"terluka":37,"menderita":13605,"mengungsi":304,"rumah":4298,"pendidikan":11,"kesehatan":1,"peribadatan":9,"fasum":0,"perkantoran":0,"jembatan":1,"pabrik":0,"kios":4,"jenis_bencana":"Puting Beliung","tahun":2020},{"id":5,"wilayah":"Jawa Tengah","jumlah_kejadian_bencana":306,"meninggal":3,"hilang":0,"terluka":42,"menderita":2038,"mengungsi":127,"rumah":2446,"pendidikan":19,"kesehatan":1,"peribadatan":8,"fasum":0,"perkantoran":1,"jembatan":1,"pabrik":0,"kios":33,"jenis_bencana":"Puting Beliung","tahun":2020},{"id":4,"wilayah":"DI Yogyakarta","jumlah_kejadian_bencana":23,"meninggal":1,"hilang":0,"terluka":4,"menderita":603,"mengungsi":0,"rumah":333,"pendidikan":1,"kesehatan":3,"peribadatan":4,"fasum":0,"perkantoran":2,"jembatan":0,"pabrik":0,"kios":5,"jenis_bencana":"Puting Beliung","tahun":2020},{"id":7,"wilayah":"Jawa Timur","jumlah_kejadian_bencana":82,"meninggal":5,"hilang":0,"terluka":15,"menderita":1635,"mengungsi":62,"rumah":1778,"pendidikan":5,"kesehatan":1,"peribadatan":14,"fasum":0,"perkantoran":4,"jembatan":0,"pabrik":0,"kios":18,"jenis_bencana":"Puting Beliung","tahun":2020},{"id":6,"wilayah":"Banten","jumlah_kejadian_bencana":38,"meninggal":0,"hilang":0,"terluka":3,"menderita":743,"mengungsi":15,"rumah":184,"pendidikan":4,"kesehatan":0,"peribadatan":4,"fasum":0,"perkantoran":0,"jembatan":0,"pabrik":0,"kios":5,"jenis_bencana":"Puting Beliung","tahun":2020},{"id":15,"wilayah":"Bali","jumlah_kejadian_bencana":57,"meninggal":0,"hilang":0,"terluka":7,"menderita":145,"mengungsi":0,"rumah":119,"pendidikan":0,"kesehatan":1,"peribadatan":13,"fasum":0,"perkantoran":1,"jembatan":0,"pabrik":0,"kios":1,"jenis_bencana":"Puting Beliung","tahun":2020},{"id":1,"wilayah":"Nusa Tenggara Barat","jumlah_kejadian_bencana":28,"meninggal":0,"hilang":0,"terluka":19,"menderita":1698,"mengungsi":0,"rumah":458,"pendidikan":1,"kesehatan":1,"peribadatan":4,"fasum":0,"perkantoran":1,"jembatan":0,"pabrik":0,"kios":0,"jenis_bencana":"Puting Beliung","tahun":2020},{"id":14,"wilayah":"Nusa Tenggara Timur","jumlah_kejadian_bencana":8,"meninggal":0,"hilang":0,"terluka":3,"menderita":286,"mengungsi":0,"rumah":158,"pendidikan":3,"kesehatan":0,"peribadatan":1,"fasum":0,"perkantoran":0,"jembatan":0,"pabrik":0,"kios":0,"jenis_bencana":"Puting Beliung","tahun":2020},{"id":30,"wilayah":"Kalimantan Barat","jumlah_kejadian_bencana":18,"meninggal":1,"hilang":0,"terluka":3,"menderita":150,"mengungsi":45,"rumah":1075,"pendidikan":1,"kesehatan":0,"peribadatan":1,"fasum":0,"perkantoran":0,"jembatan":1,"pabrik":0,"kios":0,"jenis_bencana":"Puting Beliung","tahun":2020},{"id":31,"wilayah":"Kalimantan Tengah","jumlah_kejadian_bencana":2,"meninggal":0,"hilang":0,"terluka":1,"menderita":4,"mengungsi":0,"rumah":0,"pendidikan":0,"kesehatan":0,"peribadatan":0,"fasum":0,"perkantoran":0,"jembatan":0,"pabrik":0,"kios":0,"jenis_bencana":"Puting Beliung","tahun":2020},{"id":32,"wilayah":"Kalimantan Selatan","jumlah_kejadian_bencana":42,"meninggal":0,"hilang":0,"terluka":5,"menderita":589,"mengungsi":0,"rumah":192,"pendidikan":1,"kesehatan":0,"peribadatan":2,"fasum":0,"perkantoran":0,"jembatan":0,"pabrik":0,"kios":9,"jenis_bencana":"Puting Beliung","tahun":2020},{"id":33,"wilayah":"Kalimantan Timur","jumlah_kejadian_bencana":7,"meninggal":0,"hilang":0,"terluka":0,"menderita":10,"mengungsi":0,"rumah":68,"pendidikan":0,"kesehatan":0,"peribadatan":1,"fasum":0,"perkantoran":0,"jembatan":0,"pabrik":0,"kios":0,"jenis_bencana":"Puting Beliung","tahun":2020},{"id":34,"wilayah":"Kalimantan Utara","jumlah_kejadian_bencana":8,"meninggal":0,"hilang":0,"terluka":0,"menderita":2,"mengungsi":6,"rumah":16,"pendidikan":0,"kesehatan":0,"peribadatan":0,"fasum":0,"perkantoran":0,"jembatan":0,"pabrik":0,"kios":5,"jenis_bencana":"Puting Beliung","tahun":2020},{"id":20,"wilayah":"Sulawesi Utara","jumlah_kejadian_bencana":4,"meninggal":0,"hilang":0,"terluka":0,"menderita":0,"mengungsi":0,"rumah":41,"pendidikan":2,"kesehatan":0,"peribadatan":0,"fasum":0,"perkantoran":0,"jembatan":0,"pabrik":0,"kios":0,"jenis_bencana":"Puting Beliung","tahun":2020},{"id":19,"wilayah":"Sulawesi Tengah","jumlah_kejadian_bencana":2,"meninggal":0,"hilang":0,"terluka":0,"menderita":20,"mengungsi":0,"rumah":11,"pendidikan":0,"kesehatan":0,"peribadatan":0,"fasum":0,"perkantoran":0,"jembatan":0,"pabrik":0,"kios":0,"jenis_bencana":"Puting Beliung","tahun":2020},{"id":10,"wilayah":"Sulawesi Selatan","jumlah_kejadian_bencana":78,"meninggal":1,"hilang":0,"terluka":4,"menderita":2575,"mengungsi":1,"rumah":4635,"pendidikan":13,"kesehatan":3,"peribadatan":2,"fasum":0,"perkantoran":5,"jembatan":0,"pabrik":0,"kios":59,"jenis_bencana":"Puting Beliung","tahun":2020},{"id":3,"wilayah":"Sulawesi Tenggara","jumlah_kejadian_bencana":7,"meninggal":0,"hilang":0,"terluka":0,"menderita":100,"mengungsi":50,"rumah":153,"pendidikan":0,"kesehatan":0,"peribadatan":0,"fasum":0,"perkantoran":0,"jembatan":0,"pabrik":0,"kios":0,"jenis_bencana":"Puting Beliung","tahun":2020},{"id":2,"wilayah":"Gorontalo","jumlah_kejadian_bencana":2,"meninggal":0,"hilang":0,"terluka":2,"menderita":84,"mengungsi":0,"rumah":19,"pendidikan":0,"kesehatan":0,"peribadatan":0,"fasum":0,"perkantoran":0,"jembatan":0,"pabrik":0,"kios":0,"jenis_bencana":"Puting Beliung","tahun":2020},{"id":18,"wilayah":"Sulawesi Barat","jumlah_kejadian_bencana":3,"meninggal":0,"hilang":0,"terluka":0,"menderita":63,"mengungsi":0,"rumah":12,"pendidikan":0,"kesehatan":0,"peribadatan":0,"fasum":0,"perkantoran":0,"jembatan":0,"pabrik":0,"kios":0,"jenis_bencana":"Puting Beliung","tahun":2020},{"id":9,"wilayah":"Maluku","jumlah_kejadian_bencana":5,"meninggal":0,"hilang":0,"terluka":1,"menderita":92,"mengungsi":0,"rumah":14,"pendidikan":0,"kesehatan":1,"peribadatan":0,"fasum":0,"perkantoran":0,"jembatan":0,"pabrik":0,"kios":0,"jenis_bencana":"Puting Beliung","tahun":2020},{"id":21,"wilayah":"Papua Barat","jumlah_kejadian_bencana":1,"meninggal":0,"hilang":0,"terluka":0,"menderita":0,"mengungsi":0,"rumah":6,"pendidikan":0,"kesehatan":0,"peribadatan":0,"fasum":0,"perkantoran":0,"jembatan":0,"pabrik":0,"kios":0,"jenis_bencana":"Puting Beliung","tahun":2020},{"id":13,"wilayah":"Papua","jumlah_kejadian_bencana":1,"meninggal":1,"hilang":0,"terluka":0,"menderita":10,"mengungsi":0,"rumah":2,"pendidikan":0,"kesehatan":0,"peribadatan":0,"fasum":0,"perkantoran":0,"jembatan":0,"pabrik":0,"kios":0,"jenis_bencana":"Puting Beliung","tahun":2020}],"Tanah Longsor":[{"id":29,"wilayah":"Aceh","jumlah_kejadian_bencana":19,"meninggal":2,"hilang":0,"terluka":0,"menderita":2317,"mengungsi":218,"rumah":115,"pendidikan":0,"kesehatan":0,"peribadatan":0,"fasum":0,"perkantoran":0,"jembatan":3,"pabrik":0,"kios":0,"jenis_bencana":"Tanah Longsor","tahun":2020},{"id":22,"wilayah":"Sumatera Utara","jumlah_kejadian_bencana":11,"meninggal":4,"hilang":0,"terluka":8,"menderita":1770,"mengungsi":134,"rumah":84,"pendidikan":0,"kesehatan":0,"peribadatan":2,"fasum":0,"perkantoran":0,"jembatan":1,"pabrik":0,"kios":0,"jenis_bencana":"Tanah Longsor","tahun":2020},{"id":24,"wilayah":"Sumatera Barat","jumlah_kejadian_bencana":55,"meninggal":16,"hilang":0,"terluka":2,"menderita":160,"mengungsi":49,"rumah":84,"pendidikan":1,"kesehatan":1,"peribadatan":3,"fasum":0,"perkantoran":0,"jembatan":4,"pabrik":0,"kios":0,"jenis_bencana":"Tanah Longsor","tahun":2020},{"id":16,"wilayah":"Riau","jumlah_kejadian_bencana":5,"meninggal":0,"hilang":0,"terluka":0,"menderita":35,"mengungsi":103,"rumah":24,"pendidikan":0,"kesehatan":0,"peribadatan":0,"fasum":0,"perkantoran":0,"jembatan":0,"pabrik":0,"kios":0,"jenis_bencana":"Tanah Longsor","tahun":2020},{"id":26,"wilayah":"Jambi","jumlah_kejadian_bencana":1,"meninggal":0,"hilang":0,"terluka":0,"menderita":2,"mengungsi":0,"rumah":1,"pendidikan":0,"kesehatan":0,"peribadatan":0,"fasum":0,"perkantoran":0,"jembatan":0,"pabrik":0,"kios":0,"jenis_bencana":"Tanah Longsor","tahun":2020},{"id":25,"wilayah":"Sumatera Selatan","jumlah_kejadian_bencana":12,"meninggal":13,"hilang":1,"terluka":0,"menderita":95,"mengungsi":0,"rumah":26,"pendidikan":0,"kesehatan":0,"peribadatan":0,"fasum":0,"perkantoran":0,"jembatan":0,"pabrik":0,"kios":0,"jenis_bencana":"Tanah Longsor","tahun":2020},{"id":28,"wilayah":"Bengkulu","jumlah_kejadian_bencana":7,"meninggal":0,"hilang":0,"terluka":0,"menderita":81,"mengungsi":0,"rumah":28,"pendidikan":0,"kesehatan":0,"peribadatan":1,"fasum":0,"perkantoran":0,"jembatan":5,"pabrik":0,"kios":0,"jenis_bencana":"Tanah Longsor","tahun":2020},{"id":27,"wilayah":"Lampung","jumlah_kejadian_bencana":3,"meninggal":0,"hilang":0,"terluka":0,"menderita":0,"mengungsi":0,"rumah":4,"pendidikan":0,"kesehatan":0,"peribadatan":0,"fasum":0,"perkantoran":0,"jembatan":0,"pabrik":0,"kios":0,"jenis_bencana":"Tanah Longsor","tahun":2020},{"id":23,"wilayah":"Bangka Belitung","jumlah_kejadian_bencana":5,"meninggal":10,"hilang":0,"terluka":0,"menderita":0,"mengungsi":0,"rumah":0,"pendidikan":0,"kesehatan":0,"peribadatan":0,"fasum":0,"perkantoran":0,"jembatan":0,"pabrik":0,"kios":0,"jenis_bencana":"Tanah Longsor","tahun":2020},{"id":12,"wilayah":"Jawa Barat","jumlah_kejadian_bencana":407,"meninggal":17,"hilang":0,"terluka":46,"menderita":8945,"mengungsi":1532,"rumah":1124,"pendidikan":5,"kesehatan":1,"peribadatan":3,"fasum":0,"perkantoran":1,"jembatan":8,"pabrik":0,"kios":0,"jenis_bencana":"Tanah Longsor","tahun":2020},{"id":5,"wilayah":"Jawa Tengah","jumlah_kejadian_bencana":462,"meninggal":19,"hilang":0,"terluka":33,"menderita":9794,"mengungsi":2762,"rumah":1488,"pendidikan":18,"kesehatan":1,"peribadatan":17,"fasum":0,"perkantoran":1,"jembatan":28,"pabrik":0,"kios":22,"jenis_bencana":"Tanah Longsor","tahun":2020},{"id":4,"wilayah":"DI Yogyakarta","jumlah_kejadian_bencana":8,"meninggal":0,"hilang":0,"terluka":0,"menderita":39,"mengungsi":3,"rumah":13,"pendidikan":0,"kesehatan":0,"peribadatan":0,"fasum":0,"perkantoran":0,"jembatan":1,"pabrik":0,"kios":0,"jenis_bencana":"Tanah Longsor","tahun":2020},{"id":7,"wilayah":"Jawa Timur","jumlah_kejadian_bencana":19,"meninggal":1,"hilang":0,"terluka":0,"menderita":368,"mengungsi":124,"rumah":112,"pendidikan":0,"kesehatan":0,"peribadatan":0,"fasum":0,"perkantoran":0,"jembatan":1,"pabrik":0,"kios":10,"jenis_bencana":"Tanah Longsor","tahun":2020},{"id":6,"wilayah":"Banten","jumlah_kejadian_bencana":14,"meninggal":0,"hilang":0,"terluka":0,"menderita":137,"mengungsi":0,"rumah":44,"pendidikan":1,"kesehatan":0,"peribadatan":1,"fasum":0,"perkantoran":0,"jembatan":1,"pabrik":0,"kios":0,"jenis_bencana":"Tanah Longsor","tahun":2020},{"id":15,"wilayah":"Bali","jumlah_kejadian_bencana":33,"meninggal":3,"hilang":0,"terluka":3,"menderita":40,"mengungsi":0,"rumah":51,"pendidikan":0,"kesehatan":0,"peribadatan":2,"fasum":0,"perkantoran":0,"jembatan":0,"pabrik":0,"kios":0,"jenis_bencana":"Tanah Longsor","tahun":2020},{"id":1,"wilayah":"Nusa Tenggara Barat","jumlah_kejadian_bencana":7,"meninggal":0,"hilang":0,"terluka":2,"menderita":9,"mengungsi":0,"rumah":7,"pendidikan":0,"kesehatan":0,"peribadatan":0,"fasum":0,"perkantoran":0,"jembatan":1,"pabrik":0,"kios":0,"jenis_bencana":"Tanah Longsor","tahun":2020},{"id":30,"wilayah":"Kalimantan Barat","jumlah_kejadian_bencana":4,"meninggal":0,"hilang":0,"terluka":0,"menderita":10,"mengungsi":205,"rumah":8,"pendidikan":0,"kesehatan":0,"peribadatan":0,"fasum":0,"perkantoran":0,"jembatan":0,"pabrik":0,"kios":0,"jenis_bencana":"Tanah Longsor","tahun":2020},{"id":31,"wilayah":"Kalimantan Tengah","jumlah_kejadian_bencana":1,"meninggal":3,"hilang":7,"terluka":0,"menderita":0,"mengungsi":0,"rumah":0,"pendidikan":0,"kesehatan":0,"peribadatan":0,"fasum":0,"perkantoran":0,"jembatan":0,"pabrik":0,"kios":0,"jenis_bencana":"Tanah Longsor","tahun":2020},{"id":32,"wilayah":"Kalimantan Selatan","jumlah_kejadian_bencana":4,"meninggal":0,"hilang":0,"terluka":0,"menderita":61,"mengungsi":3,"rumah":4,"pendidikan":0,"kesehatan":0,"peribadatan":0,"fasum":0,"perkantoran":0,"jembatan":0,"pabrik":0,"kios":0,"jenis_bencana":"Tanah Longsor","tahun":2020},{"id":33,"wilayah":"Kalimantan Timur","jumlah_kejadian_bencana":22,"meninggal":0,"hilang":0,"terluka":0,"menderita":81,"mengungsi":0,"rumah":56,"pendidikan":2,"kesehatan":0,"peribadatan":2,"fasum":0,"perkantoran":0,"jembatan":1,"pabrik":0,"kios":0,"jenis_bencana":"Tanah Longsor","tahun":2020},{"id":34,"wilayah":"Kalimantan Utara","jumlah_kejadian_bencana":13,"meninggal":11,"hilang":0,"terluka":3,"menderita":430,"mengungsi":0,"rumah":67,"pendidikan":0,"kesehatan":0,"peribadatan":0,"fasum":0,"perkantoran":0,"jembatan":3,"pabrik":0,"kios":0,"jenis_bencana":"Tanah Longsor","tahun":2020},{"id":20,"wilayah":"Sulawesi Utara","jumlah_kejadian_bencana":2,"meninggal":0,"hilang":0,"terluka":0,"menderita":11,"mengungsi":8,"rumah":5,"pendidikan":0,"kesehatan":0,"peribadatan":0,"fasum":0,"perkantoran":0,"jembatan":0,"pabrik":0,"kios":0,"jenis_bencana":"Tanah Longsor","tahun":2020},{"id":19,"wilayah":"Sulawesi Tengah","jumlah_kejadian_bencana":5,"meninggal":0,"hilang":0,"terluka":1,"menderita":55,"mengungsi":16,"rumah":17,"pendidikan":0,"kesehatan":0,"peribadatan":0,"fasum":0,"perkantoran":0,"jembatan":0,"pabrik":0,"kios":0,"jenis_bencana":"Tanah Longsor","tahun":2020},{"id":10,"wilayah":"Sulawesi Selatan","jumlah_kejadian_bencana":30,"meninggal":12,"hilang":0,"terluka":5,"menderita":774,"mengungsi":48,"rumah":67,"pendidikan":2,"kesehatan":1,"peribadatan":0,"fasum":0,"perkantoran":1,"jembatan":1,"pabrik":0,"kios":1,"jenis_bencana":"Tanah Longsor","tahun":2020},{"id":3,"wilayah":"Sulawesi Tenggara","jumlah_kejadian_bencana":2,"meninggal":0,"hilang":0,"terluka":0,"menderita":10,"mengungsi":0,"rumah":2,"pendidikan":0,"kesehatan":0,"peribadatan":0,"fasum":0,"perkantoran":0,"jembatan":0,"pabrik":0,"kios":0,"jenis_bencana":"Tanah Longsor","tahun":2020},{"id":18,"wilayah":"Sulawesi Barat","jumlah_kejadian_bencana":2,"meninggal":3,"hilang":0,"terluka":4,"menderita":1310,"mengungsi":0,"rumah":1,"pendidikan":0,"kesehatan":0,"peribadatan":0,"fasum":0,"perkantoran":0,"jembatan":0,"pabrik":0,"kios":0,"jenis_bencana":"Tanah Longsor","tahun":2020},{"id":9,"wilayah":"Maluku","jumlah_kejadian_bencana":5,"meninggal":0,"hilang":0,"terluka":2,"menderita":391,"mengungsi":0,"rumah":19,"pendidikan":0,"kesehatan":0,"peribadatan":0,"fasum":0,"perkantoran":0,"jembatan":0,"pabrik":0,"kios":0,"jenis_bencana":"Tanah Longsor","tahun":2020},{"id":21,"wilayah":"Papua Barat","jumlah_kejadian_bencana":1,"meninggal":1,"hilang":0,"terluka":0,"menderita":0,"mengungsi":0,"rumah":1,"pendidikan":0,"kesehatan":0,"peribadatan":0,"fasum":0,"perkantoran":0,"jembatan":0,"pabrik":0,"kios":0,"jenis_bencana":"Tanah Longsor","tahun":2020},{"id":13,"wilayah":"Papua","jumlah_kejadian_bencana":1,"meninggal":0,"hilang":0,"terluka":0,"menderita":0,"mengungsi":90,"rumah":8,"pendidikan":1,"kesehatan":0,"peribadatan":1,"fasum":0,"perkantoran":0,"jembatan":6,"pabrik":0,"kios":0,"jenis_bencana":"Tanah Longsor","tahun":2020}]}